lorenztelegram-1.0.0.dist-info/METADATA
lorenztelegram-1.0.0.dist-info/WHEEL
lorenztelegram/__init__.py
lorenztelegram/configBlocks.py
lorenztelegram/telegram.py
lorenztelegram-1.0.0.dist-info/RECORD
